{"is_source_file": false, "format": "", "description": "", "external_files": [], "external_methods": [], "published": [], "classes": [], "methods": [], "calls": [], "search-terms": ["CSS", "sidebar", "styles", "CSS selectors", "UI layout"], "state": 2, "file_id": 28, "knowledge_revision": 57, "git_revision": "", "hash": "ef7b424583eeab665e6272731dcc84b5", "format-version": 4, "code-base-name": "notes_frontend", "filename": "notes_frontend/src/app/components/sidebar/sidebar.component.css", "revision_history": [{"57": ""}]}